MANIFEST.in
setup.py
docs/CONTRIBUTORS.txt
docs/HISTORY.txt
docs/LICENSE.ZPL
docs/LICENSE.txt
docs/README.txt
src/ztfy/__init__.py
src/ztfy.ldap.egg-info/PKG-INFO
src/ztfy.ldap.egg-info/SOURCES.txt
src/ztfy.ldap.egg-info/dependency_links.txt
src/ztfy.ldap.egg-info/namespace_packages.txt
src/ztfy.ldap.egg-info/not-zip-safe
src/ztfy.ldap.egg-info/requires.txt
src/ztfy.ldap.egg-info/top_level.txt
src/ztfy/ldap/__init__.py
src/ztfy/ldap/configure.zcml
src/ztfy/ldap/pool.py
src/ztfy/ldap/auth/__init__.py
src/ztfy/ldap/auth/configure.zcml
src/ztfy/ldap/auth/group.py
src/ztfy/ldap/auth/mail.py
src/ztfy/ldap/auth/search.py
src/ztfy/ldap/auth/interfaces/__init__.py
src/ztfy/ldap/locales/ztfy.ldap.pot
src/ztfy/ldap/locales/en/LC_MESSAGES/ztfy.ldap.mo
src/ztfy/ldap/locales/en/LC_MESSAGES/ztfy.ldap.po
src/ztfy/ldap/locales/fr/LC_MESSAGES/ztfy.ldap.mo
src/ztfy/ldap/locales/fr/LC_MESSAGES/ztfy.ldap.po