Metadata-Version: 1.1
Name: ztfy.ldap
Version: 0.1.3
Summary: ZTFY utilities for LDAP
Home-page: http://www.ztfy.org
Author: Thierry Florac
Author-email: tflorac@ulthar.net
License: ZPL
Platform: UNKNOWN
Classifier: Programming Language :: Python
